<?xml version="1.0"?>
<metadata xml:lang="en"><Esri><CreaDate>20220516</CreaDate><CreaTime>10571800</CreaTime><ArcGISFormat>1.0</ArcGISFormat><SyncOnce>TRUE</SyncOnce><ModDate>20220516</ModDate><ModTime>12415700</ModTime><scaleRange><minScale>150000000</minScale><maxScale>5000</maxScale></scaleRange><ArcGISProfile>ItemDescription</ArcGISProfile></Esri><tool name="ExportAttachments" displayname="ExportAttachments" toolboxalias="Export Attachments" xmlns=""><arcToolboxHelpPath>c:\program files\arcgis\pro\Resources\Help\gp</arcToolboxHelpPath><parameters><param name="fc" displayname="Main Featureclass" type="Required" direction="Input" datatype="String" expression="fc"><dialogReference>&lt;DIV STYLE="text-align:Left;"&gt;&lt;DIV&gt;&lt;DIV&gt;&lt;P&gt;&lt;SPAN&gt;Featureclass containing all attribute data for the photos. Can be a file geodatabase or a sync copy .goedatabase sqlte file pulled down from AGOL. &lt;/SPAN&gt;&lt;/P&gt;&lt;/DIV&gt;&lt;/DIV&gt;&lt;/DIV&gt;</dialogReference></param><param name="attachment_table" displayname="Attachment Table" type="Required" direction="Input" datatype="String" expression="attachment_table"><dialogReference>&lt;DIV STYLE="text-align:Left;"&gt;&lt;DIV&gt;&lt;DIV&gt;&lt;P&gt;&lt;SPAN&gt;Related table that stores the BLOB image data.  Usually has the same name as the featureclass with __ATTACH suffix. &lt;/SPAN&gt;&lt;/P&gt;&lt;/DIV&gt;&lt;/DIV&gt;&lt;/DIV&gt;</dialogReference></param><param name="output_dir" displayname="Output Directory" type="Required" direction="Input" datatype="String" expression="output_dir"><dialogReference>&lt;DIV STYLE="text-align:Left;"&gt;&lt;DIV&gt;&lt;DIV&gt;&lt;P&gt;&lt;SPAN&gt;Folder location to store exported photos.&lt;/SPAN&gt;&lt;/P&gt;&lt;/DIV&gt;&lt;/DIV&gt;&lt;/DIV&gt;</dialogReference></param><param name="field_list" displayname="Field List" type="Optional" direction="Input" datatype="Multiple Value" expression="{field_list;field_list...}"><dialogReference>&lt;DIV STYLE="text-align:Left;"&gt;&lt;DIV&gt;&lt;DIV&gt;&lt;P&gt;&lt;SPAN&gt;List of fields that will be exported in the name of each photo.  For example, if a field called "Condition" was selected, you will see Condition_Good.jpg or something similar as the output filename.  Try to keep this just to fields you need, otherwise the file name can get huge. &lt;/SPAN&gt;&lt;/P&gt;&lt;/DIV&gt;&lt;/DIV&gt;&lt;/DIV&gt;</dialogReference></param></parameters><summary>&lt;DIV STYLE="text-align:Left;"&gt;&lt;DIV&gt;&lt;DIV&gt;&lt;P&gt;&lt;SPAN&gt;Batch exports all photos from an ArcGIS Online feature service (if attachments are enabled). The attachment table is limited in information and all attributes about the photos are in the original featureclass of the project. In order to make this data useful during the export  process, the featureclass attribute table needs to be made accessible via a pandas data frame and accessed with a lookup of the associated GUID. I've found the most success creating an offline sync copy of the project in Pro. This allows you to make edits to the attribute table and have an entire copy of the attachments locally.  You will need to change this to reflect the path to the .geodatabase file made during sync.&lt;/SPAN&gt;&lt;/P&gt;&lt;/DIV&gt;&lt;/DIV&gt;&lt;/DIV&gt;</summary></tool><dataIdInfo><idCitation><resTitle>ExportAttachments</resTitle></idCitation><searchKeys><keyword>nps</keyword></searchKeys></dataIdInfo><distInfo><distributor><distorFormat><formatName>ArcToolbox Tool</formatName></distorFormat></distributor></distInfo><mdHrLv><ScopeCd value="005"/></mdHrLv><mdDateSt Sync="TRUE">20220516</mdDateSt></metadata>
